py_listmonk/__about__.py
py_listmonk/__init__.py
py_listmonk/converter.py
py_listmonk/main.py
py_listmonk/py.typed
py_listmonk/api_resources/__init__.py
py_listmonk/api_resources/subscribers.py
py_listmonk-0.0.1.dist-info/METADATA
py_listmonk-0.0.1.dist-info/WHEEL
py_listmonk-0.0.1.dist-info/licenses/LICENSE.txt
py_listmonk-0.0.1.dist-info/RECORD
