Metadata-Version: 2.1
Name: py-listmonk
Version: 0.0.1
Summary: A python sdk for listmonk.app api.
Project-URL: Documentation, https://github.com/Tobi-De/py-listmonk#readme
Project-URL: Issues, https://github.com/Tobi-De/py-listmonk/issues
Project-URL: Source, https://github.com/Tobi-De/py-listmonk
Author-email: Tobi DEGNON <tobidegnon@proton.me>
License-Expression: MIT
License-File: LICENSE.txt
Keywords: API,JSON,Mailing List,Newsletter,Python,REST,SDK
Classifier: Development Status :: 4 - Beta
Classifier: Programming Language :: Python
Classifier: Programming Language :: Python :: 3.7
Classifier: Programming Language :: Python :: 3.8
Classifier: Programming Language :: Python :: 3.9
Classifier: Programming Language :: Python :: 3.10
Classifier: Programming Language :: Python :: 3.11
Classifier: Programming Language :: Python :: Implementation :: CPython
Classifier: Programming Language :: Python :: Implementation :: PyPy
Requires-Python: >=3.7
Requires-Dist: attrs
Requires-Dist: cattrs
Requires-Dist: httpx
Requires-Dist: pendulum
